<level type="section">
  <num>31-3931.18</num>
  <heading>Rating organization.</heading>
  <text>A captive insurer shall not be required to join a rating organization.</text>
  <level type="annotations">
    <level>
      <heading>History</heading>
      <text>(Mar. 17, 2005, D.C. Law 15-262, § 19, 52 DCR 1205; Mar. 10, 2015, D.C. Law 20-203, § 2(l), 61 DCR 12572.)</text>
    </level>
    <level>
      <heading>Section References</heading>
      <text>This section is referenced in § 31-3932.03.</text>
    </level>
    <level>
      <heading>Effect of Amendments</heading>
      <text>The 2015 amendment by D.C. Law 20-203 substituted "shall not be" for "shall not."</text>
    </level>
    <level>
      <heading>Emergency Legislation</heading>
      <text>For temporary (90 day) addition of section, see § 19 of Captive Insurance Company Emergency Act of 2004 (D.C. Act 15-640, November 30, 2004, 52 DCR 1238).</text>
    </level>
    <level>
      <heading>Legislative History of Law 15-262</heading>
      <text>For Law 15-262, see notes following § 31-3931.01.</text>
    </level>
    <level>
      <heading>Legislative History of Law 20-203</heading>
      <text>See note to § 31-3931.01.</text>
    </level>
  </level>
</level>
