<level type="section">
  <num>26-1161.03</num>
  <heading>Form and contents of application.</heading>
  <level>
    <num>(a)</num>
    <text>An application shall be filed on a form prescribed by the Commissioner. (b) Solely for purposes of and as needed for participating in the NMLS, the Commissioner is authorized to waive or modify by rule any requirements for applications, fees, or renewals in Chapter 1A, 3, 9, 10, or 11 of the Banking Code and to establish by rule new regulatory requirements as are reasonably necessary to participate in the NMLS.</text>
  </level>
  <level type="annotations">
    <level>
      <heading>History</heading>
      <text>(Mar. 7, 2015, D.C. Law 20-172, ยง 4, 61 DCR 12577.)</text>
    </level>
    <level>
      <heading>Legislative History of Law 20-172</heading>
      <text>See note to ยง 26-1161.01</text>
    </level>
  </level>
</level>
